gradio_rerun/__init__.py
gradio_rerun/events.py
gradio_rerun/py.typed
gradio_rerun/rerun.py
gradio_rerun/rerun.pyi
gradio_rerun/templates/component/index.js
gradio_rerun/templates/component/re_viewer-C0q1xlo7.js
gradio_rerun/templates/component/style.css
gradio_rerun/templates/example/index.js
gradio_rerun/templates/example/style.css
gradio_rerun-0.29.0.dist-info/METADATA
gradio_rerun-0.29.0.dist-info/WHEEL
gradio_rerun-0.29.0.dist-info/RECORD
