Metadata-Version: 2.4
Name: gradio_rerun
Version: 0.29.0
Summary: Rerun viewer with Gradio
Project-URL: repository, https://github.com/rerun-io/gradio-rerun-viewer
Project-URL: space, https://huggingface.co/spaces/rerun/gradio-rerun-viewer
Author-email: Radamés Ajna <radamajna@gmail.com>, "rerun.io" <opensource@rerun.io>
License: MIT OR Apache-2.0
Keywords: Rerun,gradio-custom-component,machine learning,multimodal data,rerun-viewer,robotics,visualization
Classifier: Development Status :: 3 - Alpha
Classifier: Operating System :: OS Independent
Classifier: Programming Language :: Python :: 3
Classifier: Programming Language :: Python :: 3 :: Only
Classifier: Programming Language :: Python :: 3.8
Classifier: Programming Language :: Python :: 3.9
Classifier: Programming Language :: Python :: 3.10
Classifier: Programming Language :: Python :: 3.11
Classifier: Topic :: Scientific/Engineering
Classifier: Topic :: Scientific/Engineering :: Artificial Intelligence
Classifier: Topic :: Scientific/Engineering :: Visualization
Requires-Python: >=3.10
Requires-Dist: gradio>=6.0.0
Requires-Dist: opencv-python
Requires-Dist: rerun-sdk==0.29.0
Requires-Dist: twine>=6.1.0
Provides-Extra: dev
Requires-Dist: build; extra == 'dev'
Requires-Dist: opencv-python>=4.10.0; extra == 'dev'
Requires-Dist: twine; extra == 'dev'
